README.txt
setup.cfg
setup.py
collective/__init__.py
collective.autogroup.egg-info/PKG-INFO
collective.autogroup.egg-info/SOURCES.txt
collective.autogroup.egg-info/dependency_links.txt
collective.autogroup.egg-info/namespace_packages.txt
collective.autogroup.egg-info/not-zip-safe
collective.autogroup.egg-info/requires.txt
collective.autogroup.egg-info/top_level.txt
collective/autogroup/README.txt
collective/autogroup/__init__.py
collective/autogroup/base.py
collective/autogroup/config.py
collective/autogroup/configure.zcml
collective/autogroup/interfaces.py
collective/autogroup/utils.py
collective/autogroup/tests/__init__.py
collective/autogroup/tests/base.py
collective/autogroup/tests/test_doc.py
docs/HISTORY.txt