Metadata-Version: 1.0
Name: collective.autogroup
Version: 0.1b1
Summary: Provide a simple API to create automatic groups in Plone.
Home-page: http://svn.plone.org/svn/collective/collective.contentgroup
Author: Rafael Oliveira
Author-email: rafaelbco@gmail.com
License: GPL
Keywords: plone groups users
Platform: UNKNOWN
Classifier: Framework :: Plone
Classifier: Programming Language :: Python
Classifier: Topic :: Software Development :: Libraries :: Python Modules
